{"blog_name":"staff","id":1295342454,"post_url":"http://staff.tumblr.com/post/1295342454/japanese-review","slug":"japanese-review","type":"photo","date":"2010-10-12 01:12:18 GMT","timestamp":1286845938,"state":"published","format":"html","reblog_key":"xydPH6NO","tags":[],"short_url":"http://tmblr.co/ZE5Fby1DDLjs","followed":true,"highlighted":[],"liked":false,"note_count":2704,"caption":"","image_permalink":"http://staff.tumblr.com/image/1295342454","photos":[{"caption":"","alt_sizes":[{"width":720,"height":480,"url":"http://www.tumblr.com/photo/1280/staff/1295342454/1/tumblr_la40c0chGX1qz4akg"},{"width":500,"height":333,"url":"http://24.media.tumblr.com/tumblr_la40c0chGX1qz4akgo1_500.jpg"},{"width":400,"height":267,"url":"http://24.media.tumblr.com/tumblr_la40c0chGX1qz4akgo1_400.jpg"},{"width":250,"height":167,"url":"http://37.media.tumblr.com/tumblr_la40c0chGX1qz4akgo1_250.jpg"},{"width":100,"height":67,"url":"http://24.media.tumblr.com/tumblr_la40c0chGX1qz4akgo1_100.jpg"},{"width":75,"height":75,"url":"http://24.media.tumblr.com/tumblr_la40c0chGX1qz4akgo1_75sq.jpg"}],"original_size":{"width":720,"height":480,"url":"http://www.tumblr.com/photo/1280/staff/1295342454/1/tumblr_la40c0chGX1qz4akg"}}],"can_reply":false}